[
    {
        "Call": "9A5AA",
        "Locator": "JN75XT",
        "Name": "Dragan",
        "Antenna": "2.4m dish offset",
        "Power": "35W",
        "Website": "",
        "Coordinates": "45.8125,15.958333",
        "Note": "",
        "DXCC": "Croatia",
        "CK": "t92YuwWah12ZAFWY1EWOuF2ZhJHZ"
    },
    {
        "Call": "BA7NQ",
        "Locator": "OL63NA",
        "Name": "Terry",
        "Antenna": "2.4m dish",
        "Power": "50W",
        "Website": "",
        "Coordinates": "23.020833,113.125",
        "Note": "",
        "DXCC": "China",
        "CK": "t92YuwWah12ZAlTO1Enb3EmY"
    },
    {
        "Call": "BD4SY",
        "Locator": "PM01JP",
        "Name": "Zhu",
        "Antenna": "3m dish",
        "Power": "30W",
        "Website": "",
        "Coordinates": "31.645833,120.791667",
        "Note": "",
        "DXCC": "China",
        "CK": "==QbvNmL2ITMAl3c0QmY"
    },
    {
        "Call": "CT1BYM",
        "Locator": "IM68BN",
        "Name": "Miguel",
        "Antenna": "3m dish",
        "Power": "120W",
        "Website": "",
        "Coordinates": "38.5625,-7.875",
        "Note": "",
        "DXCC": "Portugal",
        "CK": "==QbvNmLslWYtdGQv5WYjlGblBnLsVWdnlWb"
    },
    {
        "Call": "CT1DMK",
        "Locator": "IN50RO",
        "Name": "Luis",
        "Antenna": "5.6m dish",
        "Power": "50W",
        "Website": "",
        "Coordinates": "40.604167,-8.541667",
        "Note": "",
        "DXCC": "Portugal",
        "CK": "==QbvNmLslWYtdGQr1GZxQ3Y"
    },
    {
        "Call": "CX2SC",
        "Locator": "GF25MQ",
        "Name": "Ric",
        "Antenna": "1.8m dish offset",
        "Power": "40W",
        "Website": "",
        "Coordinates": "-34.3125,-54.958333",
        "Note": "",
        "DXCC": "Uruguay",
        "CK": "=02bj5CbpFWbnBUZzFmYuM2cyg3Y"
    },
    {
        "Call": "DB6NT",
        "Locator": "JO50VJ",
        "Name": "Michael",
        "Antenna": "3.7m dish",
        "Power": "100W",
        "Website": "",
        "Coordinates": "50.395833,11.791667",
        "Note": "",
        "DXCC": "Germany",
        "CK": "lRmL412ZARnb2IGZ"
    },
    {
        "Call": "DF1SR",
        "Locator": "JN48MR",
        "Name": "Georg",
        "Antenna": "3.6m dish",
        "Power": "0W",
        "Website": "",
        "Coordinates": "48.729167,9.041667",
        "Note": "",
        "DXCC": "Germany",
        "CK": "lRmL412ZAJ3cxYGZ"
    },
    {
        "Call": "DF3RU",
        "Locator": "JN59UL",
        "Name": "Karl",
        "Antenna": "6m dish",
        "Power": "40W",
        "Website": "",
        "Coordinates": "49.479167,11.708333",
        "Note": "",
        "DXCC": "Germany",
        "CK": "=UGZuQXZu1WYzFGQ0RWath2Yz5CbyF2a"
    },
    {
        "Call": "DJ7FJ",
        "Locator": "JN48AG",
        "Name": "Joe",
        "Antenna": "3.3m dish",
        "Power": "30W",
        "Website": "",
        "Coordinates": "48.270833,8.041667",
        "Note": "",
        "DXCC": "Germany",
        "CK": "==QbvNmLslWYtdGQoNWYi5WZyhWZm5CcwV2c"
    },
    {
        "Call": "DL1SUZ",
        "Locator": "JO53UN",
        "Name": "Uwe",
        "Antenna": "3.2m dish",
        "Power": "40W",
        "Website": "",
        "Coordinates": "53.5625,11.708333",
        "Note": "",
        "DXCC": "Germany",
        "CK": "lRmLl5Was52btQHQ6V3cxwGZ"
    },
    {
        "Call": "DL3WDG",
        "Locator": "JN68LM",
        "Name": "Charlie",
        "Antenna": "2.4m dish",
        "Power": "70W",
        "Website": "",
        "Coordinates": "48.520833,12.958333",
        "Note": "",
        "DXCC": "Germany",
        "CK": "==QbvNmLslWYtdGQxcGZ3NzZ"
    },
    {
        "Call": "DL4DTU",
        "Locator": "JO60TR",
        "Name": "Nobert",
        "Antenna": "2.4m dish offset",
        "Power": "75W",
        "Website": "",
        "Coordinates": "50.729167,13.625",
        "Note": "",
        "DXCC": "Germany",
        "CK": "=QXZu5CetdGQ1RHZ0wGZ"
    },
    {
        "Call": "DL4MEA",
        "Locator": "JN58RI",
        "Name": "Guenter",
        "Antenna": "4.5m dish",
        "Power": "26W",
        "Website": "",
        "Coordinates": "48.354167,11.458333",
        "Note": "",
        "DXCC": "Germany",
        "CK": "==wZy9mL0F2ctFGQhVWb0wGZ"
    },
    {
        "Call": "DL6SH",
        "Locator": "JN48SW",
        "Name": "Slawek",
        "Antenna": "2.4m dish",
        "Power": "50W",
        "Website": "http://www.dl6sh.com",
        "Coordinates": "48.9375,9.541667",
        "Note": "",
        "DXCC": "Germany",
        "CK": "lRmLl5Was52bAh2c2wGZ"
    },
    {
        "Call": "DL7YC",
        "Locator": "JO62PK",
        "Name": "Manfred",
        "Antenna": "4.9m dish",
        "Power": "115W",
        "Website": "",
        "Coordinates": "52.4375,13.291667",
        "Note": "",
        "DXCC": "Germany",
        "CK": "lRmL1ZWYuNHQ6RXZvxGc"
    },
    {
        "Call": "DU3T",
        "Locator": "PK04IW",
        "Name": "Ron",
        "Antenna": "4.6m dish",
        "Power": "50W",
        "Website": "",
        "Coordinates": "14.9375,120.708333",
        "Note": "",
        "DXCC": "Philippines",
        "CK": "=UGZuQXZuVWZyZGQjBnYu9mc"
    },
    {
        "Call": "EA3XU",
        "Locator": "JN11CK",
        "Name": "Benjamin",
        "Antenna": "1.5m dish offset",
        "Power": "30W",
        "Website": "",
        "Coordinates": "41.4375,2.208333",
        "Note": "",
        "DXCC": "Spain",
        "CK": "==Adl5mLhNWau9mZlxWZ0BUYt9GbhBnY"
    },
    {
        "Call": "ES5PC",
        "Locator": "KO38HJ",
        "Name": "Viljo",
        "Antenna": "4.5m dish",
        "Power": "50W",
        "Website": "",
        "Coordinates": "58.395833,26.625",
        "Note": "",
        "DXCC": "Estonia",
        "CK": "lNnL0Vmbt92YA9maslmd"
    },
    {
        "Call": "F1PYR",
        "Locator": "JN19DA",
        "Name": "Andre",
        "Antenna": "3.5m dish",
        "Power": "40W",
        "Website": "",
        "Coordinates": "49.020833,2.291667",
        "Note": "",
        "DXCC": "France",
        "CK": "==QbvNmLwlGZvZmbpBEdsVXYuNXZuUmck5WY"
    },
    {
        "Call": "F2CT",
        "Locator": "IN93GJ",
        "Name": "Guy",
        "Antenna": "3.7m dish",
        "Power": "80W",
        "Website": "",
        "Coordinates": "43.395833,-1.458333",
        "Note": "",
        "DXCC": "France",
        "CK": "yZmLv9GZh5WY3BEdjJjZ"
    },
    {
        "Call": "F5FEN",
        "Locator": "JN25JC",
        "Name": "Gilles",
        "Antenna": "6m dish",
        "Power": "0W",
        "Website": "",
        "Coordinates": "45.104167,4.791667",
        "Note": "",
        "DXCC": "France",
        "CK": ""
    },
    {
        "Call": "F5HRY",
        "Locator": "JN18EQ",
        "Name": "Herve",
        "Antenna": "2.6m dish",
        "Power": "0W",
        "Website": "",
        "Coordinates": "48.6875,2.375",
        "Note": "",
        "DXCC": "France",
        "CK": "==gcm5ybvRWYuF2dAlncoVjZ"
    },
    {
        "Call": "F5IGK",
        "Locator": "JN09NJ",
        "Name": "Alain",
        "Antenna": "2.4m dish offset",
        "Power": "40W",
        "Website": "",
        "Coordinates": "49.395833,1.125",
        "Note": "",
        "DXCC": "France",
        "CK": "==gcm5SZlJnZAt2ZpVjZ"
    },
    {
        "Call": "G3LTF",
        "Locator": "IO91GG",
        "Name": "Peter",
        "Antenna": "K. 6m dish",
        "Power": "40W",
        "Website": "",
        "Coordinates": "51.270833,-1.458333",
        "Note": "",
        "DXCC": "England",
        "CK": "=02bj5Cdl5mclRnbpRnYAZGdsNzZ"
    },
    {
        "Call": "G4CCH",
        "Locator": "IO93RM",
        "Name": "Howard",
        "Antenna": "5.4m dish",
        "Power": "25W",
        "Website": "",
        "Coordinates": "53.520833,-0.541667",
        "Note": "",
        "DXCC": "England",
        "CK": "==QbvNmLoN2Y0cGQkJXY39Ga"
    },
    {
        "Call": "G4IDR",
        "Locator": "IO93BP",
        "Name": "David",
        "Antenna": "2.4m dish",
        "Power": "12W",
        "Website": "",
        "Coordinates": "53.645833,-1.875",
        "Note": "",
        "DXCC": "England",
        "CK": "=02bj5CbpFWbnBkcklGNn5WYtRWZyRWa2FGZ"
    },
    {
        "Call": "G4LDR",
        "Locator": "IO91EC",
        "Name": "Neil",
        "Antenna": "3.8m dish",
        "Power": "100W",
        "Website": "",
        "Coordinates": "51.104167,-1.625",
        "Note": "",
        "DXCC": "England",
        "CK": "=02bj5Cdl5mclRnbpRnYAJHZsRzZ"
    },
    {
        "Call": "G4NNS",
        "Locator": "IO91FF",
        "Name": "Brian",
        "Antenna": "3.7m dish",
        "Power": "25W",
        "Website": "",
        "Coordinates": "51.229167,-1.541667",
        "Note": "",
        "DXCC": "England",
        "CK": "rVnLvNmLpxWYjNXa0Bkbh1WZs92Yt4WYpJnY"
    },
    {
        "Call": "G4RFR",
        "Locator": "IO90AS",
        "Name": "John",
        "Antenna": "3.6m dish",
        "Power": "40W",
        "Website": "",
        "Coordinates": "50.770833,-1.958333",
        "Note": "",
        "DXCC": "England",
        "CK": "=02bj5CbpFWbnBUawFGMn5ibo9ma"
    },
    {
        "Call": "HB9Q",
        "Locator": "JN47CG",
        "Name": "Daniel",
        "Antenna": "A. 10m dish",
        "Power": "100W",
        "Website": "https://hb9q.ch",
        "Coordinates": "47.270833,8.208333",
        "Note": "",
        "DXCC": "Switzerland",
        "CK": "=g2YuEXOihGQuFGZ"
    },
    {
        "Call": "I6PNN",
        "Locator": "JN72BL",
        "Name": "Amato",
        "Antenna": "4m dish",
        "Power": "28W",
        "Website": "",
        "Coordinates": "42.479167,14.125",
        "Note": "",
        "DXCC": "Italy",
        "CK": ""
    },
    {
        "Call": "IK0HWJ",
        "Locator": "JN61HM",
        "Name": "Gino",
        "Antenna": "2.4m dish",
        "Power": "150W",
        "Website": "",
        "Coordinates": "41.520833,12.625",
        "Note": "",
        "DXCC": "Italy",
        "CK": "==Adp5ibpRHQqdHawsWa"
    },
    {
        "Call": "IK2RTI",
        "Locator": "JN55AD",
        "Name": "Gianfranco",
        "Antenna": "4.8m dish",
        "Power": "100W",
        "Website": "",
        "Coordinates": "45.145833,10.041667",
        "Note": "",
        "DXCC": "Italy",
        "CK": "=QXauU2YpxWYAlGbsVmY1JXYj5ybj5WYyZmbhl2Z"
    },
    {
        "Call": "IK3COJ",
        "Locator": "JN65BN",
        "Name": "Aldo",
        "Antenna": "4.1m dish",
        "Power": "20W",
        "Website": "http://www.qsl.net/ik3coj",
        "Coordinates": "45.5625,12.125",
        "Note": "",
        "DXCC": "Italy",
        "CK": "==QbvNmLslWYtdGQq92YzsWa"
    },
    {
        "Call": "IZ2DJP",
        "Locator": "JN55FO",
        "Name": "Adelio",
        "Antenna": "3m dish",
        "Power": "15W",
        "Website": "",
        "Coordinates": "45.604167,10.458333",
        "Note": "",
        "DXCC": "Italy",
        "CK": "==Adp5ybyVmYpxGQlRWYyVGd"
    },
    {
        "Call": "JA1WQF",
        "Locator": "QM05AV",
        "Name": "Mitsuo",
        "Antenna": "2.4m dish",
        "Power": "100W",
        "Website": "",
        "Coordinates": "35.895833,140.041667",
        "Note": "",
        "DXCC": "Japan",
        "CK": "=AnauUmbu42bpRmL1QGQmF3dxEma"
    },
    {
        "Call": "JA4BLC",
        "Locator": "PM65NM",
        "Name": "Yoshiro",
        "Antenna": "2.4m dish offset",
        "Power": "120W",
        "Website": "",
        "Coordinates": "35.520833,133.125",
        "Note": "",
        "DXCC": "Japan",
        "CK": "==Acq5ybj5ibp5WYz1iYldHQjxmY0Ema"
    },
    {
        "Call": "JA6AHB",
        "Locator": "PM53CP",
        "Name": "Toshio",
        "Antenna": "3m dish",
        "Power": "100W",
        "Website": "https://ja6ahb.com",
        "Coordinates": "33.645833,130.208333",
        "Note": "",
        "DXCC": "Japan",
        "CK": "vRnLhxWYsBHQihWY2Ema"
    },
    {
        "Call": "JA6XED",
        "Locator": "PM53FH",
        "Name": "Hisao",
        "Antenna": "5m dish",
        "Power": "50W",
        "Website": "",
        "Coordinates": "33.3125,130.458333",
        "Note": "",
        "DXCC": "Japan",
        "CK": "==Acq5SZu5ibp1WdrBEZlhnNhpGOzEzMrRHa"
    },
    {
        "Call": "JA7BMB",
        "Locator": "PM97WM",
        "Name": "Hiroshi",
        "Antenna": "4m dish",
        "Power": "10W",
        "Website": "",
        "Coordinates": "37.520833,139.875",
        "Note": "",
        "DXCC": "Japan",
        "CK": ""
    },
    {
        "Call": "JA8ERE",
        "Locator": "QN02QX",
        "Name": "Mikio",
        "Antenna": "4.5m dish",
        "Power": "80W",
        "Website": "",
        "Coordinates": "42.979167,141.375",
        "Note": "",
        "DXCC": "Japan",
        "CK": "t92YukHdmlmbAFTMwEDMsd2c"
    },
    {
        "Call": "JF3HUC",
        "Locator": "PM74UX",
        "Name": "Yoshitaka",
        "Antenna": "6m dish",
        "Power": "50W",
        "Website": "",
        "Coordinates": "34.979167,135.708333",
        "Note": "",
        "DXCC": "Japan",
        "CK": "==QbvNmL5RnZp5GQjVHazYma"
    },
    {
        "Call": "JH7OPT",
        "Locator": "QM07DI",
        "Name": "Masa",
        "Antenna": "1.2m dish",
        "Power": "2W",
        "Website": "",
        "Coordinates": "37.354167,140.291667",
        "Note": "",
        "DXCC": "Japan",
        "CK": "t92YuwmchpGQ0B3b3gma"
    },
    {
        "Call": "JS6UJS",
        "Locator": "PL24CK",
        "Name": "Ochial",
        "Antenna": "1.6m dish",
        "Power": "100W",
        "Website": "",
        "Coordinates": "24.4375,124.208333",
        "Note": "",
        "DXCC": "Japan",
        "CK": "=QXZu5SYyVGcv1GQ3p3c4Ema"
    },
    {
        "Call": "KL6M",
        "Locator": "BP51DC",
        "Name": "Mike",
        "Antenna": "9.2m dish",
        "Power": "50W",
        "Website": "",
        "Coordinates": "61.104167,-149.708333",
        "Note": "",
        "DXCC": "Alaska",
        "CK": "==QbvNmLtZDbrBUZrlWb"
    },
    {
        "Call": "KN0WS",
        "Locator": "EN34KW",
        "Name": "Carl",
        "Antenna": "2.4m dish",
        "Power": "50W",
        "Website": "",
        "Coordinates": "44.9375,-93.125",
        "Note": "",
        "DXCC": "United States",
        "CK": "==QbvNmLxBkbldmchJ2chhGbyF2Y"
    },
    {
        "Call": "LA8LF",
        "Locator": "JO59BS",
        "Name": "Anders",
        "Antenna": "4.6m dish",
        "Power": "40W",
        "Website": "",
        "Coordinates": "59.770833,10.125",
        "Note": "",
        "DXCC": "Norway",
        "CK": "==QbvNmLmxGOhxGQzJXZk5WY"
    },
    {
        "Call": "LX1DB",
        "Locator": "JN39CO",
        "Name": "Willy",
        "Antenna": "3m dish",
        "Power": "250W",
        "Website": "",
        "Coordinates": "49.604167,6.208333",
        "Note": "",
        "DXCC": "Luxembourg",
        "CK": "1xmL0BHQyVWdhJ2d"
    },
    {
        "Call": "LZ1DX",
        "Locator": "KN22TK",
        "Name": "Ned",
        "Antenna": "5.4m dish",
        "Power": "9W",
        "Website": "",
        "Coordinates": "42.4375,25.625",
        "Note": "",
        "DXCC": "Bulgaria",
        "CK": "nJ3bugHZxoHbAhHZxoHb"
    },
    {
        "Call": "LZ4OC",
        "Locator": "KN33KG",
        "Name": "Sasho",
        "Antenna": "1.8m dish",
        "Power": "40W",
        "Website": "",
        "Coordinates": "43.270833,26.875",
        "Note": "",
        "DXCC": "Bulgaria",
        "CK": "nJmL2JWYAN2b0oHb"
    },
    {
        "Call": "M0FXX",
        "Locator": "IO91NM",
        "Name": "Robert",
        "Antenna": "3m dish",
        "Power": "10W",
        "Website": "",
        "Coordinates": "51.520833,-0.875",
        "Note": "",
        "DXCC": "England",
        "CK": "=02bj5Cdl5mclRnbpRnYAJWbpxmL0JXZi9mc"
    },
    {
        "Call": "OE5VRL",
        "Locator": "JN78DK",
        "Name": "Rudi",
        "Antenna": "3m dish",
        "Power": "30W",
        "Website": "",
        "Coordinates": "48.4375,14.291667",
        "Note": "",
        "DXCC": "Austria",
        "CK": "0Vmbu42bhBkcldmbpJGbvtWY35SakVnc"
    },
    {
        "Call": "OE9ERC",
        "Locator": "JN47VL",
        "Name": "Erich",
        "Antenna": "11m dish offset",
        "Power": "50W",
        "Website": "http://www.oe9erc.com",
        "Coordinates": "47.479167,9.791667",
        "Note": "",
        "DXCC": "Austria",
        "CK": "==QbvNmLjJXZ5U2bAh2YpJXZ"
    },
    {
        "Call": "OH1LRY",
        "Locator": "KP11AE",
        "Name": "Janne",
        "Antenna": "4m dish",
        "Power": "50W",
        "Website": "",
        "Coordinates": "61.1875,22.041667",
        "Note": "",
        "DXCC": "Finland",
        "CK": "==QbvNmLslWYtdGQ5JHbxg2b"
    },
    {
        "Call": "OH2DG",
        "Locator": "KP30CK",
        "Name": "Eino",
        "Antenna": "3m dish",
        "Power": "100W",
        "Website": "",
        "Coordinates": "60.4375,26.208333",
        "Note": "",
        "DXCC": "Finland",
        "CK": "=02bj5CbpFWbnB0bulWZptWYtF2c0VWb"
    },
    {
        "Call": "OH3LWP",
        "Locator": "KP11XK",
        "Name": "Ari",
        "Antenna": "4m dish",
        "Power": "70W",
        "Website": "",
        "Coordinates": "61.4375,23.958333",
        "Note": "",
        "DXCC": "Finland",
        "CK": "=kmZukmb1RHQuVmbhNXahZnLpJXY"
    },
    {
        "Call": "OK1CS",
        "Locator": "JO70FD",
        "Name": "Emil",
        "Antenna": "4.5m dish",
        "Power": "0W",
        "Website": "http://ok1cs.cz",
        "Coordinates": "50.145833,14.458333",
        "Note": "",
        "DXCC": "Czech Republic",
        "CK": "t92YuwWah12ZAN3Yxs2b"
    },
    {
        "Call": "OK1DFC",
        "Locator": "JN79GW",
        "Name": "Zdenek",
        "Antenna": "2.4m dish offset",
        "Power": "120W",
        "Website": "http://www.ok1dfc.com",
        "Coordinates": "49.9375,14.541667",
        "Note": "",
        "DXCC": "Czech Republic",
        "CK": "==gej5Sbh5melNHQjZGZxs2b"
    },
    {
        "Call": "OK1IN",
        "Locator": "JO60XE",
        "Name": "Petr",
        "Antenna": "3m dish",
        "Power": "50W",
        "Website": "",
        "Coordinates": "50.1875,13.958333",
        "Note": "",
        "DXCC": "Czech Republic",
        "CK": "6NmLtFmb6V2cA5Waxs2b"
    },
    {
        "Call": "OK1KIR",
        "Locator": "JN79DW",
        "Name": "Tonda",
        "Antenna": "/ Vlada 6.1m dish",
        "Power": "65W",
        "Website": "",
        "Coordinates": "49.9375,14.291667",
        "Note": "",
        "DXCC": "Czech Republic",
        "CK": "=o3Yuknbs9mdAtWZzFWbuIXatlGZhxmd"
    },
    {
        "Call": "ON5RR",
        "Locator": "JO20CX",
        "Name": "Marc",
        "Antenna": "6m dish",
        "Power": "100W",
        "Website": "",
        "Coordinates": "50.979167,4.208333",
        "Note": "",
        "DXCC": "Belgium",
        "CK": "t92YuwWah12ZA52buIXZj5WdvJmbv9Wb"
    },
    {
        "Call": "ON5TA",
        "Locator": "JO20ES",
        "Name": "Eric",
        "Antenna": "2.4m dish offset",
        "Power": "25W",
        "Website": "",
        "Coordinates": "50.770833,4.375",
        "Note": "",
        "DXCC": "Belgium",
        "CK": "==QbvNmLslWYtdGQuVGblZmZv5WY25yYpJXZ"
    },
    {
        "Call": "OZ1LPR",
        "Locator": "JO44UW",
        "Name": "Peter",
        "Antenna": "2.4m dish offset",
        "Power": "500W",
        "Website": "http://www.oz1lpr.dk",
        "Coordinates": "54.9375,9.708333",
        "Note": "",
        "DXCC": "Denmark",
        "CK": "=sGZuwWah1GQyBHbxo3b"
    },
    {
        "Call": "PA0BAT",
        "Locator": "JO31FX",
        "Name": "Gerard",
        "Antenna": "3.7m dish",
        "Power": "100W",
        "Website": "",
        "Coordinates": "51.979167,6.458333",
        "Note": "",
        "DXCC": "Netherlands",
        "CK": "s5mL5F2dpF2YAtmbpNXZldmLkJXYyV2Z"
    },
    {
        "Call": "PA0PLY",
        "Locator": "JO32LR",
        "Name": "Jan",
        "Antenna": "3m dish",
        "Power": "50W",
        "Website": "http://www.pa0ply.nl",
        "Coordinates": "52.729167,6.958333",
        "Note": "",
        "DXCC": "Netherlands",
        "CK": "=wmbukHbwBTYwB0bm5Wa"
    },
    {
        "Call": "PA3DZL",
        "Locator": "JO21LS",
        "Name": "Jac",
        "Antenna": "3.7m dish",
        "Power": "110W",
        "Website": "",
        "Coordinates": "51.770833,4.958333",
        "Note": "",
        "DXCC": "Netherlands",
        "CK": "=02bj5CZ19GbjlGQMpFRzEEU"
    },
    {
        "Call": "PA7JB",
        "Locator": "JO22MD",
        "Name": "John",
        "Antenna": "2.4m dish offset",
        "Power": "50W",
        "Website": "",
        "Coordinates": "52.145833,5.041667",
        "Note": "",
        "DXCC": "Netherlands",
        "CK": "=wmbu82ZnlmeAJma3EGc"
    },
    {
        "Call": "PE1CKK",
        "Locator": "JO22OF",
        "Name": "Hans",
        "Antenna": "1.8m dish offset",
        "Power": "100W",
        "Website": "",
        "Coordinates": "52.229167,5.208333",
        "Note": "",
        "DXCC": "Netherlands",
        "CK": "=wmbuQXZuRXZoB0aul2cs9Ga"
    },
    {
        "Call": "PY1KK",
        "Locator": "GG76GS",
        "Name": "Bruce",
        "Antenna": "4m dish",
        "Power": "60W",
        "Website": "",
        "Coordinates": "-23.229167,-45.458333",
        "Note": "",
        "DXCC": "Brazil",
        "CK": "t92Yus2bylmeAV2Y1JnY"
    },
    {
        "Call": "PY2BS",
        "Locator": "GG66PJ",
        "Name": "Bruce",
        "Antenna": "3.7m dish",
        "Power": "60W",
        "Website": "",
        "Coordinates": "-23.604167,-46.708333",
        "Note": "",
        "DXCC": "Brazil",
        "CK": "t92Yus2bylmeAV2Y1JnY"
    },
    {
        "Call": "R3YAS",
        "Locator": "KO72PI",
        "Name": "Alex",
        "Antenna": "3m dish",
        "Power": "200W",
        "Website": "",
        "Coordinates": "52.354167,35.291667",
        "Note": "",
        "DXCC": "European Russia",
        "CK": "=UncuwWah1GQl1WZzEmc"
    },
    {
        "Call": "R5AN",
        "Locator": "KO86FE",
        "Name": "Artem",
        "Antenna": "1.9m dish",
        "Power": "80W",
        "Website": "",
        "Coordinates": "56.1875,36.458333",
        "Note": "",
        "DXCC": "European Russia",
        "CK": "1JnLslWYtBkbhVjc"
    },
    {
        "Call": "RA3EME",
        "Locator": "KO72PI",
        "Name": "Alex",
        "Antenna": "5m dish",
        "Power": "200W",
        "Website": "",
        "Coordinates": "52.354167,35.291667",
        "Note": "",
        "DXCC": "European Russia",
        "CK": "=UncuwWah1GQl1WZzEmc"
    },
    {
        "Call": "RK3T",
        "Locator": "LO61QW",
        "Name": "Nick",
        "Antenna": "1.4m dish",
        "Power": "12W",
        "Website": "",
        "Coordinates": "51.9375,53.375",
        "Note": "",
        "DXCC": "European Russia",
        "CK": "1JnLslWYtBEdzsmc"
    },
    {
        "Call": "S57NML",
        "Locator": "JN76OD",
        "Name": "Andrej",
        "Antenna": "3m dish",
        "Power": "35W",
        "Website": "",
        "Coordinates": "46.145833,15.208333",
        "Note": "",
        "DXCC": "Slovenia",
        "CK": "=02bj5CbpFWbnBEZlZHZl1WY"
    },
    {
        "Call": "S57RA",
        "Locator": "JN75AP",
        "Name": "Pavel",
        "Antenna": "3m dish",
        "Power": "20W",
        "Website": "",
        "Coordinates": "45.645833,14.041667",
        "Note": "",
        "DXCC": "Slovenia",
        "CK": "=k2cu8WakFmctFGaAFmc3Uzc"
    },
    {
        "Call": "S59DCD",
        "Locator": "JN76NL",
        "Name": "Silvo",
        "Antenna": "6.1m dish",
        "Power": "30W",
        "Website": "",
        "Coordinates": "46.479167,15.125",
        "Note": "",
        "DXCC": "Slovenia",
        "CK": "==QbvNmLslWYtdGQkNGZ5Uzc"
    },
    {
        "Call": "SA6BUN",
        "Locator": "JO78CP",
        "Name": "Michael",
        "Antenna": "3m dish",
        "Power": "120W",
        "Website": "",
        "Coordinates": "58.645833,14.208333",
        "Note": "",
        "DXCC": "Sweden",
        "CK": "==QbvNmLslWYtdGQuVnY2E2c"
    },
    {
        "Call": "SG6W",
        "Locator": "JO67AQ",
        "Name": "Ingolf",
        "Antenna": "5.5m dish",
        "Power": "100W",
        "Website": "",
        "Coordinates": "57.6875,12.041667",
        "Note": "",
        "DXCC": "Sweden",
        "CK": "=02bj5CbpFWbnBkeoZmLmx2bn5Wa"
    },
    {
        "Call": "SM4DHN",
        "Locator": "JP60VD",
        "Name": "Lars-Berti",
        "Antenna": "6m dish",
        "Power": "60W",
        "Website": "",
        "Coordinates": "60.145833,13.791667",
        "Note": "",
        "DXCC": "Sweden",
        "CK": "lNnLoNWZ0VmYhxGQuhGZ002c"
    },
    {
        "Call": "SM6CKU",
        "Locator": "JO67CK",
        "Name": "Bengt-Arne",
        "Antenna": "4m dish",
        "Power": "40W",
        "Website": "",
        "Coordinates": "57.4375,12.208333",
        "Note": "",
        "DXCC": "Sweden",
        "CK": "=U2cuQnclt2YvpGQ1t2Y202c"
    },
    {
        "Call": "SM6FHZ",
        "Locator": "JO67AQ",
        "Name": "Ingolf",
        "Antenna": "5.5m dish",
        "Power": "100W",
        "Website": "",
        "Coordinates": "57.6875,12.041667",
        "Note": "",
        "DXCC": "Sweden",
        "CK": "=02bj5CbpFWbnBkeoZmLmx2bn5Wa"
    },
    {
        "Call": "SM6PGP",
        "Locator": "JO67BK",
        "Name": "Hannes",
        "Antenna": "2.3m dish",
        "Power": "80W",
        "Website": "",
        "Coordinates": "57.4375,12.125",
        "Note": "",
        "DXCC": "Sweden",
        "CK": "==QZz5SZwlGbslGQwdGc202c"
    },
    {
        "Call": "SP2HMR",
        "Locator": "JO94FK",
        "Name": "Marcel",
        "Antenna": "3m dish",
        "Power": "25W",
        "Website": "",
        "Coordinates": "54.4375,18.458333",
        "Note": "",
        "DXCC": "Poland",
        "CK": "sBnLlBUb"
    },
    {
        "Call": "SP3XBO",
        "Locator": "JO81XR",
        "Name": "Marek",
        "Antenna": "3m dish",
        "Power": "30W",
        "Website": "",
        "Coordinates": "51.729167,17.958333",
        "Note": "",
        "DXCC": "Poland",
        "CK": "sBnLw9GQvJGezA3c"
    },
    {
        "Call": "SP6GWN",
        "Locator": "JO80GL",
        "Name": "Henryk",
        "Antenna": "3.3m dish",
        "Power": "36W",
        "Website": "http://sp6gwn.qrz.pl",
        "Coordinates": "50.479167,16.541667",
        "Note": "",
        "DXCC": "Poland",
        "CK": "sBnLwdHQud3Z2A3c"
    },
    {
        "Call": "SP6JLW",
        "Locator": "JO80JK",
        "Name": "Andrzej",
        "Antenna": "4m dish",
        "Power": "25W",
        "Website": "",
        "Coordinates": "50.4375,16.791667",
        "Note": "",
        "DXCC": "Poland",
        "CK": "sBnLwdHQ3xma2A3c"
    },
    {
        "Call": "SP7JSG",
        "Locator": "KO01BW",
        "Name": "Stan",
        "Antenna": "4m dish",
        "Power": "0W",
        "Website": "",
        "Coordinates": "51.9375,20.125",
        "Note": "",
        "DXCC": "Poland",
        "CK": "sBnLt92YuUGdhdGdl5GQid3Z2A3c"
    },
    {
        "Call": "SP9VFD",
        "Locator": "JN99XN",
        "Name": "Rafal",
        "Antenna": "6.4m dish",
        "Power": "37W",
        "Website": "",
        "Coordinates": "49.5625,19.958333",
        "Note": "",
        "DXCC": "Poland",
        "CK": "==QbvNmLv9GahlHQkZmd5A3c"
    },
    {
        "Call": "SQ6OPG",
        "Locator": "JO80JK",
        "Name": "Paul",
        "Antenna": "4m dish",
        "Power": "70W",
        "Website": "",
        "Coordinates": "50.4375,16.791667",
        "Note": "",
        "DXCC": "Poland",
        "CK": ""
    },
    {
        "Call": "SV1BTR",
        "Locator": "KM18NO",
        "Name": "Jimmy",
        "Antenna": "4.9m dish",
        "Power": "0W",
        "Website": "",
        "Coordinates": "38.604167,23.125",
        "Note": "",
        "DXCC": "Greece",
        "CK": "==gcn5CbvhGQ2lXbtlma"
    },
    {
        "Call": "SV3AAF",
        "Locator": "KM17KO",
        "Name": "Petros",
        "Antenna": "3.9m dish",
        "Power": "80W",
        "Website": "",
        "Coordinates": "37.604167,22.875",
        "Note": "",
        "DXCC": "Greece",
        "CK": "702bj5CbpFWb0V2aj9mcAd2bpdGc"
    },
    {
        "Call": "TM8PB",
        "Locator": "IN88FS",
        "Name": "Guy",
        "Antenna": "13.5m dish",
        "Power": "80W",
        "Website": "",
        "Coordinates": "48.770833,-3.541667",
        "Note": "",
        "DXCC": "France",
        "CK": "yZmLv9GZh5WY3BEdjJjZ"
    },
    {
        "Call": "UA3PTW",
        "Locator": "KO93BS",
        "Name": "Dimitrij",
        "Antenna": "5.8m dish",
        "Power": "0W",
        "Website": "",
        "Coordinates": "53.770833,38.125",
        "Note": "",
        "DXCC": "European Russia",
        "CK": "1JnL49mYulGQ3RHczEWd"
    },
    {
        "Call": "UA4AAV",
        "Locator": "LO21FD",
        "Name": "Victor",
        "Antenna": "2.5m dish",
        "Power": "15W",
        "Website": "",
        "Coordinates": "51.145833,44.458333",
        "Note": "",
        "DXCC": "European Russia",
        "CK": "=UncuwWah1GQ2FWY0EWd"
    },
    {
        "Call": "UA5Y",
        "Locator": "KO72PI",
        "Name": "Alexander",
        "Antenna": "3m dish",
        "Power": "200W",
        "Website": "",
        "Coordinates": "52.354167,35.291667",
        "Note": "",
        "DXCC": "European Russia",
        "CK": "=UncuwWah1GQmd3dzsmc"
    },
    {
        "Call": "UN6PD",
        "Locator": "MN69JM",
        "Name": "Nikolai",
        "Antenna": "2.4m dish offset",
        "Power": "50W",
        "Website": "",
        "Coordinates": "49.520833,72.791667",
        "Note": "",
        "DXCC": "Kazakhstan",
        "CK": "=Uncug3bi5WaARGc24Wd"
    },
    {
        "Call": "UR7D",
        "Locator": "KN18DO",
        "Name": "Vlad",
        "Antenna": "3.7m dish",
        "Power": "0W",
        "Website": "",
        "Coordinates": "48.604167,22.291667",
        "Note": "",
        "DXCC": "Ukraine",
        "CK": "=sTdy5CbpFWbApHZ1oXd"
    },
    {
        "Call": "VE4MA",
        "Locator": "EN19LU",
        "Name": "Barry",
        "Antenna": "2.4m dish offset",
        "Power": "190W",
        "Website": "",
        "Coordinates": "49.854167,-97.041667",
        "Note": "",
        "DXCC": "Canada",
        "CK": "==QYj5ydhh2cAFWb0Umd"
    },
    {
        "Call": "VE4MA/K7",
        "Locator": "DM43FK",
        "Name": "Barry",
        "Antenna": "1.5m dish",
        "Power": "150W",
        "Website": "",
        "Coordinates": "33.4375,-111.541667",
        "Note": "",
        "DXCC": "United States",
        "CK": "=02bj5CbpFWbnBUYtRTZ2lncyFmY"
    },
    {
        "Call": "VE6BGT",
        "Locator": "DO32FK",
        "Name": "Skip",
        "Antenna": "6.4m dish",
        "Power": "100W",
        "Website": "",
        "Coordinates": "52.4375,-113.541667",
        "Note": "",
        "DXCC": "Canada",
        "CK": "=02bj5CbpFWbnBEcpt2cukXYsVXYjFWb"
    },
    {
        "Call": "VE6TA",
        "Locator": "DO33GS",
        "Name": "Grant",
        "Antenna": "5.5m dish",
        "Power": "100W",
        "Website": "",
        "Coordinates": "53.770833,-113.458333",
        "Note": "",
        "DXCC": "Canada",
        "CK": "hNmLlZXY3JXYlx2YAFGd2Umd"
    },
    {
        "Call": "VK3NX",
        "Locator": "QF21CT",
        "Name": "Charlie",
        "Antenna": "3.7m dish",
        "Power": "100W",
        "Website": "http://www.vk3nx.com",
        "Coordinates": "-38.1875,144.208333",
        "Note": "",
        "DXCC": "Australia",
        "CK": "=UXYuQXZu5CZu9GcnlmYA1WayF2auJWa"
    },
    {
        "Call": "W5LUA",
        "Locator": "EM13QC",
        "Name": "Al",
        "Antenna": "5m dish",
        "Power": "80W",
        "Website": "",
        "Coordinates": "33.104167,-96.625",
        "Note": "",
        "DXCC": "United States",
        "CK": "==Adl5mLsFmYvx2ZjJ2cAFWdsVzd"
    },
    {
        "Call": "WA3RGQ",
        "Locator": "EL98EB",
        "Name": "Don",
        "Antenna": "3m dish",
        "Power": "50W",
        "Website": "",
        "Coordinates": "28.0625,-81.625",
        "Note": "",
        "DXCC": "United States",
        "CK": "=QXZu5CdzF2Yt92YAJXZrFmY3FGau9GZ"
    },
    {
        "Call": "WA5ICW",
        "Locator": "EM26",
        "Name": "Jim",
        "Antenna": "4.7m dish",
        "Power": "100W",
        "Website": "",
        "Coordinates": "36.5,-95",
        "Note": "",
        "DXCC": "United States",
        "CK": ""
    },
    {
        "Call": "WA6PY",
        "Locator": "DM13LA",
        "Name": "Paul",
        "Antenna": "3.6m dish",
        "Power": "80W",
        "Website": "",
        "Coordinates": "33.020833,-117.041667",
        "Note": "",
        "DXCC": "United States",
        "CK": "==QbvNmLyJnLuF2cANnbp12boNGc"
    },
    {
        "Call": "WA8WZG",
        "Locator": "EN81OM",
        "Name": "Tom",
        "Antenna": "4.9m dish",
        "Power": "70W",
        "Website": "",
        "Coordinates": "41.520833,-82.791667",
        "Note": "",
        "DXCC": "United States",
        "CK": "=02bj5yZ6dHOhdHQnp3d4E2d"
    },
    {
        "Call": "WA9FWD",
        "Locator": "EN53XB",
        "Name": "John",
        "Antenna": "3.7m dish",
        "Power": "100W",
        "Website": "",
        "Coordinates": "43.0625,-88.041667",
        "Note": "",
        "DXCC": "United States",
        "CK": "t92Yus2bvxGd19GQkdnZ5E2d"
    },
    {
        "Call": "WB2BYP",
        "Locator": "FN13IB",
        "Name": "John",
        "Antenna": "8.4m dish",
        "Power": "0W",
        "Website": "",
        "Coordinates": "43.0625,-77.291667",
        "Note": "",
        "DXCC": "United States",
        "CK": "==wOnJ3buUWZllGQwlnYyI2d"
    },
    {
        "Call": "WD5AGO",
        "Locator": "EM26CB",
        "Name": "Tommy",
        "Antenna": "D. 3.1m dish",
        "Power": "30W",
        "Website": "",
        "Coordinates": "36.0625,-95.791667",
        "Note": "",
        "DXCC": "United States",
        "CK": "==ALt92YuwWah1GdvhGQvdWY1Q2d"
    },
    {
        "Call": "YO8RHI",
        "Locator": "KN37SD",
        "Name": "Adi",
        "Antenna": "2.2m dish",
        "Power": "35W",
        "Website": "http://yo8rhi.blogspot.ro//",
        "Coordinates": "47.145833,27.541667",
        "Note": "",
        "DXCC": "Romania",
        "CK": "==QbvNmLv9GahlHQphmc48WepRWY"
    },
    {
        "Call": "K5DOG",
        "Locator": "EM00WH",
        "Name": "Steve",
        "Antenna": "4.4m dish",
        "Power": "10W",
        "Website": "",
        "Coordinates": "30.3125,-98.125",
        "Note": "",
        "DXCC": "United States",
        "CK": "t92Yuc2bkVzaAVmdlR3c"
    }
]