[
    {
        "Call": "AI6I",
        "Locator": "DM65XR",
        "Name": "Charles",
        "Antenna": "M2-222 5wl",
        "Power": "1000.0",
        "Website": "",
        "Coordinates": "35.729167,-106.041667",
        "Note": "",
        "DXCC": "United States",
        "CK": "==Adl5mLu9mepJXZ2BUa2kWY"
    },
    {
        "Call": "K1WHS",
        "Locator": "FN43MJ",
        "Name": "Dave",
        "Antenna": "4x22el",
        "Power": "1500.0",
        "Website": "",
        "Coordinates": "43.395833,-70.958333",
        "Note": "",
        "DXCC": "United States",
        "CK": "==Adl5mL0NXYj9mc0VWbANHa3Fza"
    },
    {
        "Call": "K3SK",
        "Locator": "FM07TH",
        "Name": "Dave",
        "Antenna": "4x12LFA",
        "Power": "1000.0",
        "Website": "",
        "Coordinates": "37.3125,-78.375",
        "Note": "",
        "DXCC": "United States",
        "CK": "vNmLyVGdsF2drNWdiB0azNza"
    },
    {
        "Call": "K9MRI",
        "Locator": "EN70IU",
        "Name": "Joe",
        "Antenna": "2x22el",
        "Power": "600.0",
        "Website": "",
        "Coordinates": "40.854167,-85.291667",
        "Note": "",
        "DXCC": "United States",
        "CK": "==Adl5mLr5WashGdyFWZAlmctlza"
    },
    {
        "Call": "KC7OOY",
        "Locator": "CN82OG",
        "Name": "Matt",
        "Antenna": "4x11LFA",
        "Power": "1000.0",
        "Website": "",
        "Coordinates": "42.270833,-122.791667",
        "Note": "",
        "DXCC": "United States",
        "CK": "=02bj5CbpFWbu9GdvJHcA5mbh12X0FWb"
    },
    {
        "Call": "KL6M",
        "Locator": "BP51DC",
        "Name": "Mike",
        "Antenna": "9.2m dish",
        "Power": "1000.0",
        "Website": "",
        "Coordinates": "61.104167,-149.708333",
        "Note": "",
        "DXCC": "Alaska",
        "CK": "==Adl5mLsJnchBUb2w2a"
    },
    {
        "Call": "KM0T",
        "Locator": "EN14VB",
        "Name": "Mike",
        "Antenna": "2x5wl",
        "Power": "1200.0",
        "Website": "",
        "Coordinates": "44.0625,-96.208333",
        "Note": "",
        "DXCC": "United States",
        "CK": "==Adl5mLsJnchBEdw02a"
    },
    {
        "Call": "N0AKC",
        "Locator": "EN44",
        "Name": "Charles",
        "Antenna": "2x23el",
        "Power": "800.0",
        "Website": "",
        "Coordinates": "44.5,-91",
        "Note": "",
        "DXCC": "United States",
        "CK": "0VmbuIXZ0JXYoNGQ6RXZi12Y"
    },
    {
        "Call": "N1AV",
        "Locator": "DM43",
        "Name": "Jay",
        "Antenna": "4x15XP",
        "Power": "1000.0",
        "Website": "",
        "Coordinates": "33.5,-111",
        "Note": "",
        "DXCC": "United States",
        "CK": "==Adl5mLsJnchBkdhFjb"
    },
    {
        "Call": "NH6Y",
        "Locator": "BL10FS",
        "Name": "Tom",
        "Antenna": "2x15el",
        "Power": "800.0",
        "Website": "",
        "Coordinates": "20.770833,-157.541667",
        "Note": "",
        "DXCC": "Hawaii",
        "CK": "=QXZu5Sa1FWbAhGdy92d"
    },
    {
        "Call": "NX9O",
        "Locator": "EM84AO",
        "Name": "Brian",
        "Antenna": "",
        "Power": "",
        "Website": "",
        "Coordinates": "34.604167,-83.958333",
        "Note": "",
        "DXCC": "United States",
        "CK": "==Adl5mLsJnchB0b5gnb"
    },
    {
        "Call": "PJ4MM",
        "Locator": "FK52VE",
        "Name": "Martin",
        "Antenna": "2x17LFA",
        "Power": "800.0",
        "Website": "",
        "Coordinates": "12.1875,-68.208333",
        "Note": "",
        "DXCC": "Bonaire",
        "CK": "s5mLt1GNqBHQulGdyFWb"
    },
    {
        "Call": "VE6TA",
        "Locator": "DO33GS",
        "Name": "Grant",
        "Antenna": "5.5m dish",
        "Power": "750.0",
        "Website": "",
        "Coordinates": "53.770833,-113.458333",
        "Note": "",
        "DXCC": "Canada",
        "CK": "t92YuQXZuJ3bsBHeAFGd2Umd"
    },
    {
        "Call": "W2BYP",
        "Locator": "FN13IB",
        "Name": "John",
        "Antenna": "2x16el or 8.5m dish",
        "Power": "1000.0",
        "Website": "",
        "Coordinates": "43.0625,-77.291667",
        "Note": "",
        "DXCC": "United States",
        "CK": "0VmbuwmcyFGQwlnYyI2d"
    },
    {
        "Call": "W4VIC",
        "Locator": "EM84CA",
        "Name": "Victor",
        "Antenna": "4x10el",
        "Power": "500.0",
        "Website": "",
        "Coordinates": "34.020833,-83.791667",
        "Note": "",
        "DXCC": "United States",
        "CK": "==QbvNmLslWYtdGQjlmdyVmdsV3Y"
    },
    {
        "Call": "W4ZST",
        "Locator": "EM84AO",
        "Name": "Robert",
        "Antenna": "2x M2 222xp30",
        "Power": "1500.0",
        "Website": "",
        "Coordinates": "34.604167,-83.958333",
        "Note": "",
        "DXCC": "United States",
        "CK": "=QXZu5CbyJXYAR3c6Rzd"
    },
    {
        "Call": "W5AFY",
        "Locator": "EM04ID",
        "Name": "Dan",
        "Antenna": "5m dish",
        "Power": "1200.0",
        "Website": "",
        "Coordinates": "34.145833,-99.291667",
        "Note": "",
        "DXCC": "United States",
        "CK": "=QXZu5SemFWNidHQ5ZWY1I2d"
    },
    {
        "Call": "W5EME",
        "Locator": "EM32IA",
        "Name": "Rick",
        "Antenna": "2x22el FO",
        "Power": "800.0",
        "Website": "",
        "Coordinates": "32.020833,-93.291667",
        "Note": "",
        "DXCC": "United States",
        "CK": "t92Yu82boFWeARDNxc3ajlmc"
    },
    {
        "Call": "W5LUA",
        "Locator": "EM13QC",
        "Name": "Al",
        "Antenna": "7.3m dish",
        "Power": "1200.0",
        "Website": "",
        "Coordinates": "33.104167,-96.625",
        "Note": "",
        "DXCC": "United States",
        "CK": "==Adl5mLsFmYvx2ZjJ2cAFWdsVzd"
    },
    {
        "Call": "W5ZN",
        "Locator": "EM45DH",
        "Name": "Joel",
        "Antenna": "4x16el",
        "Power": "1500.0",
        "Website": "",
        "Coordinates": "35.3125,-91.708333",
        "Note": "",
        "DXCC": "United States",
        "CK": "t92YuwWah12ZAxWZvpmb6Vzd"
    },
    {
        "Call": "W6TCP",
        "Locator": "CM97EQ",
        "Name": "Ian",
        "Antenna": "4x16el",
        "Power": "900.0",
        "Website": "",
        "Coordinates": "37.6875,-121.625",
        "Note": "",
        "DXCC": "United States",
        "CK": "t92YuwWah12ZA5WYpB3Y0Zzd"
    },
    {
        "Call": "W7JW",
        "Locator": "EN82FJ",
        "Name": "Jeff",
        "Antenna": "8x14el",
        "Power": "800.0",
        "Website": "",
        "Coordinates": "42.395833,-83.541667",
        "Note": "",
        "DXCC": "United States",
        "CK": "==Adl5mLsJnchB0dqdzd"
    },
    {
        "Call": "W7TZ",
        "Locator": "CN83IA",
        "Name": "Roger",
        "Antenna": "4x15LFA",
        "Power": "1000.0",
        "Website": "",
        "Coordinates": "43.020833,-123.291667",
        "Note": "",
        "DXCC": "United States",
        "CK": "=02bj5CbpFWbnBkcld2byJXZn9mc3kWY"
    },
    {
        "Call": "W7XU",
        "Locator": "EN13LM",
        "Name": "Doc",
        "Antenna": "4x22el",
        "Power": "1000.0",
        "Website": "",
        "Coordinates": "43.520833,-97.041667",
        "Note": "",
        "DXCC": "United States",
        "CK": "==QbvNmL1h3N3BUd4dzd"
    },
    {
        "Call": "W8ZN",
        "Locator": "FM09TE",
        "Name": "Terry",
        "Antenna": "4x16el",
        "Power": "1500.0",
        "Website": "",
        "Coordinates": "39.1875,-78.375",
        "Note": "",
        "DXCC": "United States",
        "CK": "==Adl5mLsJnchBkb6hzd"
    }
]